setup.py
myip/__init__.py
myip/cmd_parsing.py
myip/darwin.py
myip/linux.py
myip/myip_cmd.py
myip/parsing.py
myip/test_myip.py
myip.egg-info/PKG-INFO
myip.egg-info/SOURCES.txt
myip.egg-info/dependency_links.txt
myip.egg-info/entry_points.txt
myip.egg-info/requires.txt
myip.egg-info/top_level.txt