Metadata-Version: 1.0
Name: myip
Version: 0.2
Summary: Simply print the IP of the current host
Home-page: http://www.github.com/orenhe/myip
Author: Oren Held
Author-email: oren@held.org.il
License: MIT
Platform: UNKNOWN
